{"cameraMode":{"drawMode":0,"name":"Shaded","section":"Shading Mode"},"sceneLighting":true,"audioPlay":false,"sceneViewState":{"m_AlwaysRefresh":false,"showFog":true,"showSkybox":false,"showFlares":true,"showImageEffects":true,"showParticleSystems":true,"showVisualEffectGraphs":true,"m_FxEnabled":true},"in2DMode":false,"pivot":{"x":17.9468994140625,"y":18.567977905273439,"z":12.05221176147461},"rotation":{"x":-0.30653682351112368,"y":0.6883511543273926,"z":-0.5108063817024231,"w":-0.4150262773036957},"size":2.158717393875122,"orthographic":false}